{
	"configurations" : 
	[
		{
			"directories" : 
			[
				{
					"build" : ".",
					"jsonFile" : "directory-.-Debug-f5ebdc15457944623624.json",
					"minimumCMakeVersion" : 
					{
						"string" : "3.29"
					},
					"projectIndex" : 0,
					"source" : ".",
					"targetIndexes" : 
					[
						0,
						1,
						2,
						3,
						4,
						5,
						6,
						7,
						8,
						9,
						10,
						11,
						12,
						13,
						14,
						15,
						16,
						17,
						18,
						19,
						20,
						21,
						22,
						23,
						24,
						25,
						26,
						27,
						28,
						29,
						30,
						31,
						32,
						33,
						34,
						35,
						36,
						37,
						38,
						39,
						40,
						41,
						42,
						43,
						44,
						45,
						46,
						47,
						48,
						49,
						50,
						51,
						52,
						53,
						54,
						55,
						56,
						57,
						58,
						59,
						60,
						61,
						62,
						63,
						64,
						65,
						66,
						67,
						68,
						69,
						70,
						71,
						72,
						73,
						74,
						75,
						76,
						77,
						78,
						79,
						80,
						81,
						82,
						83,
						84,
						85,
						86,
						87,
						88,
						89,
						90,
						91,
						92,
						93,
						94,
						95,
						96,
						97,
						98
					]
				}
			],
			"name" : "Debug",
			"projects" : 
			[
				{
					"directoryIndexes" : 
					[
						0
					],
					"name" : "C_Study",
					"targetIndexes" : 
					[
						0,
						1,
						2,
						3,
						4,
						5,
						6,
						7,
						8,
						9,
						10,
						11,
						12,
						13,
						14,
						15,
						16,
						17,
						18,
						19,
						20,
						21,
						22,
						23,
						24,
						25,
						26,
						27,
						28,
						29,
						30,
						31,
						32,
						33,
						34,
						35,
						36,
						37,
						38,
						39,
						40,
						41,
						42,
						43,
						44,
						45,
						46,
						47,
						48,
						49,
						50,
						51,
						52,
						53,
						54,
						55,
						56,
						57,
						58,
						59,
						60,
						61,
						62,
						63,
						64,
						65,
						66,
						67,
						68,
						69,
						70,
						71,
						72,
						73,
						74,
						75,
						76,
						77,
						78,
						79,
						80,
						81,
						82,
						83,
						84,
						85,
						86,
						87,
						88,
						89,
						90,
						91,
						92,
						93,
						94,
						95,
						96,
						97,
						98
					]
				}
			],
			"targets" : 
			[
				{
					"directoryIndex" : 0,
					"id" : "02::@6890427a1f51a3e7e1df",
					"jsonFile" : "target-02-Debug-8d1a2f845a521cab184a.json",
					"name" : "02",
					"projectIndex" : 0
				},
				{
					"directoryIndex" : 0,
					"id" : "03::@6890427a1f51a3e7e1df",
					"jsonFile" : "target-03-Debug-661803c2336747f3480e.json",
					"name" : "03",
					"projectIndex" : 0
				},
				{
					"directoryIndex" : 0,
					"id" : "04::@6890427a1f51a3e7e1df",
					"jsonFile" : "target-04-Debug-0d62ab1ba5baf7ede168.json",
					"name" : "04",
					"projectIndex" : 0
				},
				{
					"directoryIndex" : 0,
					"id" : "05::@6890427a1f51a3e7e1df",
					"jsonFile" : "target-05-Debug-d16d3ec071f6207b0eb9.json",
					"name" : "05",
					"projectIndex" : 0
				},
				{
					"directoryIndex" : 0,
					"id" : "06::@6890427a1f51a3e7e1df",
					"jsonFile" : "target-06-Debug-f1e81f4049593bdda47e.json",
					"name" : "06",
					"projectIndex" : 0
				},
				{
					"directoryIndex" : 0,
					"id" : "07::@6890427a1f51a3e7e1df",
					"jsonFile" : "target-07-Debug-174e1cf3673de8b1504e.json",
					"name" : "07",
					"projectIndex" : 0
				},
				{
					"directoryIndex" : 0,
					"id" : "08::@6890427a1f51a3e7e1df",
					"jsonFile" : "target-08-Debug-131ebc5290868bd4e346.json",
					"name" : "08",
					"projectIndex" : 0
				},
				{
					"directoryIndex" : 0,
					"id" : "09::@6890427a1f51a3e7e1df",
					"jsonFile" : "target-09-Debug-b0b45e9ad34370d0510f.json",
					"name" : "09",
					"projectIndex" : 0
				},
				{
					"directoryIndex" : 0,
					"id" : "1-5-1::@6890427a1f51a3e7e1df",
					"jsonFile" : "target-1-5-1-Debug-07fc32a7abbfd393926f.json",
					"name" : "1-5-1",
					"projectIndex" : 0
				},
				{
					"directoryIndex" : 0,
					"id" : "1-5-10::@6890427a1f51a3e7e1df",
					"jsonFile" : "target-1-5-10-Debug-d4ad17b8da4d9d6ca96e.json",
					"name" : "1-5-10",
					"projectIndex" : 0
				},
				{
					"directoryIndex" : 0,
					"id" : "1-5-2::@6890427a1f51a3e7e1df",
					"jsonFile" : "target-1-5-2-Debug-6f113054cb5469211588.json",
					"name" : "1-5-2",
					"projectIndex" : 0
				},
				{
					"directoryIndex" : 0,
					"id" : "1-5-3::@6890427a1f51a3e7e1df",
					"jsonFile" : "target-1-5-3-Debug-59f1c965503692baad92.json",
					"name" : "1-5-3",
					"projectIndex" : 0
				},
				{
					"directoryIndex" : 0,
					"id" : "1-5-4::@6890427a1f51a3e7e1df",
					"jsonFile" : "target-1-5-4-Debug-e77ab289f883bc62bbd3.json",
					"name" : "1-5-4",
					"projectIndex" : 0
				},
				{
					"directoryIndex" : 0,
					"id" : "1-5-5::@6890427a1f51a3e7e1df",
					"jsonFile" : "target-1-5-5-Debug-c2d435ff5c52838505de.json",
					"name" : "1-5-5",
					"projectIndex" : 0
				},
				{
					"directoryIndex" : 0,
					"id" : "1-5-6::@6890427a1f51a3e7e1df",
					"jsonFile" : "target-1-5-6-Debug-e17c9e3f578381b79923.json",
					"name" : "1-5-6",
					"projectIndex" : 0
				},
				{
					"directoryIndex" : 0,
					"id" : "1-5-7::@6890427a1f51a3e7e1df",
					"jsonFile" : "target-1-5-7-Debug-ac2a5a29a0abfc58e198.json",
					"name" : "1-5-7",
					"projectIndex" : 0
				},
				{
					"directoryIndex" : 0,
					"id" : "1-5-8::@6890427a1f51a3e7e1df",
					"jsonFile" : "target-1-5-8-Debug-958d905df881b3694932.json",
					"name" : "1-5-8",
					"projectIndex" : 0
				},
				{
					"directoryIndex" : 0,
					"id" : "1-5-9::@6890427a1f51a3e7e1df",
					"jsonFile" : "target-1-5-9-Debug-0471c4a16c0d44d99a45.json",
					"name" : "1-5-9",
					"projectIndex" : 0
				},
				{
					"directoryIndex" : 0,
					"id" : "1-6-1::@6890427a1f51a3e7e1df",
					"jsonFile" : "target-1-6-1-Debug-9d4f1f2e13b66ece7754.json",
					"name" : "1-6-1",
					"projectIndex" : 0
				},
				{
					"directoryIndex" : 0,
					"id" : "1-6-10::@6890427a1f51a3e7e1df",
					"jsonFile" : "target-1-6-10-Debug-2fb70490fa6e66e99906.json",
					"name" : "1-6-10",
					"projectIndex" : 0
				},
				{
					"directoryIndex" : 0,
					"id" : "1-6-11::@6890427a1f51a3e7e1df",
					"jsonFile" : "target-1-6-11-Debug-aee64c6dac8b9b05f8b8.json",
					"name" : "1-6-11",
					"projectIndex" : 0
				},
				{
					"directoryIndex" : 0,
					"id" : "1-6-12::@6890427a1f51a3e7e1df",
					"jsonFile" : "target-1-6-12-Debug-fbf2f82b37325f983c66.json",
					"name" : "1-6-12",
					"projectIndex" : 0
				},
				{
					"directoryIndex" : 0,
					"id" : "1-6-2::@6890427a1f51a3e7e1df",
					"jsonFile" : "target-1-6-2-Debug-38f99a7dbbdd1b59bb08.json",
					"name" : "1-6-2",
					"projectIndex" : 0
				},
				{
					"directoryIndex" : 0,
					"id" : "1-6-3::@6890427a1f51a3e7e1df",
					"jsonFile" : "target-1-6-3-Debug-a42184dd3d9875e5510e.json",
					"name" : "1-6-3",
					"projectIndex" : 0
				},
				{
					"directoryIndex" : 0,
					"id" : "1-6-4::@6890427a1f51a3e7e1df",
					"jsonFile" : "target-1-6-4-Debug-dbd245f43cdfffc2dd31.json",
					"name" : "1-6-4",
					"projectIndex" : 0
				},
				{
					"directoryIndex" : 0,
					"id" : "1-6-5::@6890427a1f51a3e7e1df",
					"jsonFile" : "target-1-6-5-Debug-9d0e0a1ee996585d90dc.json",
					"name" : "1-6-5",
					"projectIndex" : 0
				},
				{
					"directoryIndex" : 0,
					"id" : "1-6-6::@6890427a1f51a3e7e1df",
					"jsonFile" : "target-1-6-6-Debug-a913daa5888711c23687.json",
					"name" : "1-6-6",
					"projectIndex" : 0
				},
				{
					"directoryIndex" : 0,
					"id" : "1-6-7::@6890427a1f51a3e7e1df",
					"jsonFile" : "target-1-6-7-Debug-fed7ddf409cee9756468.json",
					"name" : "1-6-7",
					"projectIndex" : 0
				},
				{
					"directoryIndex" : 0,
					"id" : "1-6-8::@6890427a1f51a3e7e1df",
					"jsonFile" : "target-1-6-8-Debug-4c71a0e463e3e1cb3b5f.json",
					"name" : "1-6-8",
					"projectIndex" : 0
				},
				{
					"directoryIndex" : 0,
					"id" : "1-6-9::@6890427a1f51a3e7e1df",
					"jsonFile" : "target-1-6-9-Debug-06c7d0af06d4f81c8ef2.json",
					"name" : "1-6-9",
					"projectIndex" : 0
				},
				{
					"directoryIndex" : 0,
					"id" : "1-7-1::@6890427a1f51a3e7e1df",
					"jsonFile" : "target-1-7-1-Debug-5583d95d1649b496bb73.json",
					"name" : "1-7-1",
					"projectIndex" : 0
				},
				{
					"directoryIndex" : 0,
					"id" : "1-7-10::@6890427a1f51a3e7e1df",
					"jsonFile" : "target-1-7-10-Debug-acc19dd4916c125f5001.json",
					"name" : "1-7-10",
					"projectIndex" : 0
				},
				{
					"directoryIndex" : 0,
					"id" : "1-7-11::@6890427a1f51a3e7e1df",
					"jsonFile" : "target-1-7-11-Debug-83b441ae0a8bb7d0978d.json",
					"name" : "1-7-11",
					"projectIndex" : 0
				},
				{
					"directoryIndex" : 0,
					"id" : "1-7-12::@6890427a1f51a3e7e1df",
					"jsonFile" : "target-1-7-12-Debug-92386b237dc5fb4d8313.json",
					"name" : "1-7-12",
					"projectIndex" : 0
				},
				{
					"directoryIndex" : 0,
					"id" : "1-7-2::@6890427a1f51a3e7e1df",
					"jsonFile" : "target-1-7-2-Debug-f4dd2c13dc11be4e8e0a.json",
					"name" : "1-7-2",
					"projectIndex" : 0
				},
				{
					"directoryIndex" : 0,
					"id" : "1-7-3::@6890427a1f51a3e7e1df",
					"jsonFile" : "target-1-7-3-Debug-00a5107890329067f7f5.json",
					"name" : "1-7-3",
					"projectIndex" : 0
				},
				{
					"directoryIndex" : 0,
					"id" : "1-7-4::@6890427a1f51a3e7e1df",
					"jsonFile" : "target-1-7-4-Debug-67f6cca838ac8d02ad04.json",
					"name" : "1-7-4",
					"projectIndex" : 0
				},
				{
					"directoryIndex" : 0,
					"id" : "1-7-5::@6890427a1f51a3e7e1df",
					"jsonFile" : "target-1-7-5-Debug-d9eb0cb281841c7e29fb.json",
					"name" : "1-7-5",
					"projectIndex" : 0
				},
				{
					"directoryIndex" : 0,
					"id" : "1-7-6::@6890427a1f51a3e7e1df",
					"jsonFile" : "target-1-7-6-Debug-4dd283f17e03630eac09.json",
					"name" : "1-7-6",
					"projectIndex" : 0
				},
				{
					"directoryIndex" : 0,
					"id" : "1-7-7::@6890427a1f51a3e7e1df",
					"jsonFile" : "target-1-7-7-Debug-72f8ffe461283e291aa1.json",
					"name" : "1-7-7",
					"projectIndex" : 0
				},
				{
					"directoryIndex" : 0,
					"id" : "1-7-8::@6890427a1f51a3e7e1df",
					"jsonFile" : "target-1-7-8-Debug-1dd036018dbe86bac459.json",
					"name" : "1-7-8",
					"projectIndex" : 0
				},
				{
					"directoryIndex" : 0,
					"id" : "1-7-9::@6890427a1f51a3e7e1df",
					"jsonFile" : "target-1-7-9-Debug-f2c6558d55e44fab89c3.json",
					"name" : "1-7-9",
					"projectIndex" : 0
				},
				{
					"directoryIndex" : 0,
					"id" : "1-8-1::@6890427a1f51a3e7e1df",
					"jsonFile" : "target-1-8-1-Debug-3d4a3628b8a9f7b7b36e.json",
					"name" : "1-8-1",
					"projectIndex" : 0
				},
				{
					"directoryIndex" : 0,
					"id" : "1-8-10::@6890427a1f51a3e7e1df",
					"jsonFile" : "target-1-8-10-Debug-4f0f3dde64ea77ab5059.json",
					"name" : "1-8-10",
					"projectIndex" : 0
				},
				{
					"directoryIndex" : 0,
					"id" : "1-8-2::@6890427a1f51a3e7e1df",
					"jsonFile" : "target-1-8-2-Debug-ec6dc0c427c4bf59484b.json",
					"name" : "1-8-2",
					"projectIndex" : 0
				},
				{
					"directoryIndex" : 0,
					"id" : "1-8-3::@6890427a1f51a3e7e1df",
					"jsonFile" : "target-1-8-3-Debug-5efea7d93f77fd14a0e5.json",
					"name" : "1-8-3",
					"projectIndex" : 0
				},
				{
					"directoryIndex" : 0,
					"id" : "1-8-4::@6890427a1f51a3e7e1df",
					"jsonFile" : "target-1-8-4-Debug-47ae23716e0020d91f1c.json",
					"name" : "1-8-4",
					"projectIndex" : 0
				},
				{
					"directoryIndex" : 0,
					"id" : "1-8-5::@6890427a1f51a3e7e1df",
					"jsonFile" : "target-1-8-5-Debug-e5d24624990d5c551360.json",
					"name" : "1-8-5",
					"projectIndex" : 0
				},
				{
					"directoryIndex" : 0,
					"id" : "1-8-6::@6890427a1f51a3e7e1df",
					"jsonFile" : "target-1-8-6-Debug-fa39a23c3424747d6c00.json",
					"name" : "1-8-6",
					"projectIndex" : 0
				},
				{
					"directoryIndex" : 0,
					"id" : "1-8-7::@6890427a1f51a3e7e1df",
					"jsonFile" : "target-1-8-7-Debug-13c5c37079fa1554c283.json",
					"name" : "1-8-7",
					"projectIndex" : 0
				},
				{
					"directoryIndex" : 0,
					"id" : "1-8-7-1::@6890427a1f51a3e7e1df",
					"jsonFile" : "target-1-8-7-1-Debug-0eac919ead093e4a06b9.json",
					"name" : "1-8-7-1",
					"projectIndex" : 0
				},
				{
					"directoryIndex" : 0,
					"id" : "1-8-8::@6890427a1f51a3e7e1df",
					"jsonFile" : "target-1-8-8-Debug-dd4ea43832d2ed71751e.json",
					"name" : "1-8-8",
					"projectIndex" : 0
				},
				{
					"directoryIndex" : 0,
					"id" : "1-8-9::@6890427a1f51a3e7e1df",
					"jsonFile" : "target-1-8-9-Debug-3b79f11c0ee295cf1cf0.json",
					"name" : "1-8-9",
					"projectIndex" : 0
				},
				{
					"directoryIndex" : 0,
					"id" : "1-9-1::@6890427a1f51a3e7e1df",
					"jsonFile" : "target-1-9-1-Debug-f9d37dcf982af6d1d9a2.json",
					"name" : "1-9-1",
					"projectIndex" : 0
				},
				{
					"directoryIndex" : 0,
					"id" : "1-9-2::@6890427a1f51a3e7e1df",
					"jsonFile" : "target-1-9-2-Debug-1386d7a53e9b2bf63fba.json",
					"name" : "1-9-2",
					"projectIndex" : 0
				},
				{
					"directoryIndex" : 0,
					"id" : "1-9-3::@6890427a1f51a3e7e1df",
					"jsonFile" : "target-1-9-3-Debug-8cc901e29797683c9ceb.json",
					"name" : "1-9-3",
					"projectIndex" : 0
				},
				{
					"directoryIndex" : 0,
					"id" : "1-9-4::@6890427a1f51a3e7e1df",
					"jsonFile" : "target-1-9-4-Debug-0b9dad45a36b27fc79c3.json",
					"name" : "1-9-4",
					"projectIndex" : 0
				},
				{
					"directoryIndex" : 0,
					"id" : "1-9-5::@6890427a1f51a3e7e1df",
					"jsonFile" : "target-1-9-5-Debug-d1ca6fad296d3216f879.json",
					"name" : "1-9-5",
					"projectIndex" : 0
				},
				{
					"directoryIndex" : 0,
					"id" : "1-9-6::@6890427a1f51a3e7e1df",
					"jsonFile" : "target-1-9-6-Debug-56dd664c8d1b78b15c7e.json",
					"name" : "1-9-6",
					"projectIndex" : 0
				},
				{
					"directoryIndex" : 0,
					"id" : "2-1::@6890427a1f51a3e7e1df",
					"jsonFile" : "target-2-1-Debug-7700aedcfc472ba9c316.json",
					"name" : "2-1",
					"projectIndex" : 0
				},
				{
					"directoryIndex" : 0,
					"id" : "4-1::@6890427a1f51a3e7e1df",
					"jsonFile" : "target-4-1-Debug-3361eea9f2783f5da767.json",
					"name" : "4-1",
					"projectIndex" : 0
				},
				{
					"directoryIndex" : 0,
					"id" : "5-11::@6890427a1f51a3e7e1df",
					"jsonFile" : "target-5-11-Debug-97e740375bab14cff587.json",
					"name" : "5-11",
					"projectIndex" : 0
				},
				{
					"directoryIndex" : 0,
					"id" : "5-12::@6890427a1f51a3e7e1df",
					"jsonFile" : "target-5-12-Debug-a3548f7a5ca987955786.json",
					"name" : "5-12",
					"projectIndex" : 0
				},
				{
					"directoryIndex" : 0,
					"id" : "6-1::@6890427a1f51a3e7e1df",
					"jsonFile" : "target-6-1-Debug-0f5985eafbe82fefa58e.json",
					"name" : "6-1",
					"projectIndex" : 0
				},
				{
					"directoryIndex" : 0,
					"id" : "6-13::@6890427a1f51a3e7e1df",
					"jsonFile" : "target-6-13-Debug-7f4bc1062e1380715318.json",
					"name" : "6-13",
					"projectIndex" : 0
				},
				{
					"directoryIndex" : 0,
					"id" : "6-13-1::@6890427a1f51a3e7e1df",
					"jsonFile" : "target-6-13-1-Debug-661b64b892fd47da66aa.json",
					"name" : "6-13-1",
					"projectIndex" : 0
				},
				{
					"directoryIndex" : 0,
					"id" : "6-2::@6890427a1f51a3e7e1df",
					"jsonFile" : "target-6-2-Debug-84c8e9261d36b2c8110e.json",
					"name" : "6-2",
					"projectIndex" : 0
				},
				{
					"directoryIndex" : 0,
					"id" : "6-3::@6890427a1f51a3e7e1df",
					"jsonFile" : "target-6-3-Debug-c714246671682ff45335.json",
					"name" : "6-3",
					"projectIndex" : 0
				},
				{
					"directoryIndex" : 0,
					"id" : "6-4::@6890427a1f51a3e7e1df",
					"jsonFile" : "target-6-4-Debug-1c6b3e4179b9be859ca9.json",
					"name" : "6-4",
					"projectIndex" : 0
				},
				{
					"directoryIndex" : 0,
					"id" : "7-1::@6890427a1f51a3e7e1df",
					"jsonFile" : "target-7-1-Debug-167ee1e55b67ff189b69.json",
					"name" : "7-1",
					"projectIndex" : 0
				},
				{
					"directoryIndex" : 0,
					"id" : "7-10::@6890427a1f51a3e7e1df",
					"jsonFile" : "target-7-10-Debug-68f5763c05d464f5e48b.json",
					"name" : "7-10",
					"projectIndex" : 0
				},
				{
					"directoryIndex" : 0,
					"id" : "7-11::@6890427a1f51a3e7e1df",
					"jsonFile" : "target-7-11-Debug-79cb9c99c285f74cbf7e.json",
					"name" : "7-11",
					"projectIndex" : 0
				},
				{
					"directoryIndex" : 0,
					"id" : "7-2::@6890427a1f51a3e7e1df",
					"jsonFile" : "target-7-2-Debug-8aafbb230818c58631a1.json",
					"name" : "7-2",
					"projectIndex" : 0
				},
				{
					"directoryIndex" : 0,
					"id" : "7-3::@6890427a1f51a3e7e1df",
					"jsonFile" : "target-7-3-Debug-e38c8e43c1f1e8eb2b5a.json",
					"name" : "7-3",
					"projectIndex" : 0
				},
				{
					"directoryIndex" : 0,
					"id" : "7-3-1::@6890427a1f51a3e7e1df",
					"jsonFile" : "target-7-3-1-Debug-7e4c0eb0d6b1b34eb60b.json",
					"name" : "7-3-1",
					"projectIndex" : 0
				},
				{
					"directoryIndex" : 0,
					"id" : "7-4::@6890427a1f51a3e7e1df",
					"jsonFile" : "target-7-4-Debug-3430c26a795d100cf5e4.json",
					"name" : "7-4",
					"projectIndex" : 0
				},
				{
					"directoryIndex" : 0,
					"id" : "7-4-1::@6890427a1f51a3e7e1df",
					"jsonFile" : "target-7-4-1-Debug-84cdffbe80ac6495cbbc.json",
					"name" : "7-4-1",
					"projectIndex" : 0
				},
				{
					"directoryIndex" : 0,
					"id" : "7-5::@6890427a1f51a3e7e1df",
					"jsonFile" : "target-7-5-Debug-1fab469d25587ce878ee.json",
					"name" : "7-5",
					"projectIndex" : 0
				},
				{
					"directoryIndex" : 0,
					"id" : "7-6::@6890427a1f51a3e7e1df",
					"jsonFile" : "target-7-6-Debug-e46268403cae51fad11c.json",
					"name" : "7-6",
					"projectIndex" : 0
				},
				{
					"directoryIndex" : 0,
					"id" : "8-1::@6890427a1f51a3e7e1df",
					"jsonFile" : "target-8-1-Debug-3985c1172dba1588c95e.json",
					"name" : "8-1",
					"projectIndex" : 0
				},
				{
					"directoryIndex" : 0,
					"id" : "8-10::@6890427a1f51a3e7e1df",
					"jsonFile" : "target-8-10-Debug-4dcd39dde8e4242172ea.json",
					"name" : "8-10",
					"projectIndex" : 0
				},
				{
					"directoryIndex" : 0,
					"id" : "8-11::@6890427a1f51a3e7e1df",
					"jsonFile" : "target-8-11-Debug-0d379081429fabb71879.json",
					"name" : "8-11",
					"projectIndex" : 0
				},
				{
					"directoryIndex" : 0,
					"id" : "8-2::@6890427a1f51a3e7e1df",
					"jsonFile" : "target-8-2-Debug-fa74861bc17c07ff02dc.json",
					"name" : "8-2",
					"projectIndex" : 0
				},
				{
					"directoryIndex" : 0,
					"id" : "8-3::@6890427a1f51a3e7e1df",
					"jsonFile" : "target-8-3-Debug-a6153d17232d59ebe4b6.json",
					"name" : "8-3",
					"projectIndex" : 0
				},
				{
					"directoryIndex" : 0,
					"id" : "8-4::@6890427a1f51a3e7e1df",
					"jsonFile" : "target-8-4-Debug-13801d7745a67b3dfabc.json",
					"name" : "8-4",
					"projectIndex" : 0
				},
				{
					"directoryIndex" : 0,
					"id" : "8-5::@6890427a1f51a3e7e1df",
					"jsonFile" : "target-8-5-Debug-ef4d7213b39767f8ca52.json",
					"name" : "8-5",
					"projectIndex" : 0
				},
				{
					"directoryIndex" : 0,
					"id" : "8-6::@6890427a1f51a3e7e1df",
					"jsonFile" : "target-8-6-Debug-112f16d30702489b2e02.json",
					"name" : "8-6",
					"projectIndex" : 0
				},
				{
					"directoryIndex" : 0,
					"id" : "8-8::@6890427a1f51a3e7e1df",
					"jsonFile" : "target-8-8-Debug-157fd2f1d11e6c3b84b4.json",
					"name" : "8-8",
					"projectIndex" : 0
				},
				{
					"directoryIndex" : 0,
					"id" : "8-9::@6890427a1f51a3e7e1df",
					"jsonFile" : "target-8-9-Debug-0b642df9e46402012434.json",
					"name" : "8-9",
					"projectIndex" : 0
				},
				{
					"directoryIndex" : 0,
					"id" : "9-1::@6890427a1f51a3e7e1df",
					"jsonFile" : "target-9-1-Debug-efeb0bd28bb23f8f681c.json",
					"name" : "9-1",
					"projectIndex" : 0
				},
				{
					"directoryIndex" : 0,
					"id" : "9-2::@6890427a1f51a3e7e1df",
					"jsonFile" : "target-9-2-Debug-851afa7800cd37fb1899.json",
					"name" : "9-2",
					"projectIndex" : 0
				},
				{
					"directoryIndex" : 0,
					"id" : "CH04_4-1::@6890427a1f51a3e7e1df",
					"jsonFile" : "target-CH04_4-1-Debug-3b17170601c1156fb73d.json",
					"name" : "CH04_4-1",
					"projectIndex" : 0
				},
				{
					"directoryIndex" : 0,
					"id" : "CH05_5-11::@6890427a1f51a3e7e1df",
					"jsonFile" : "target-CH05_5-11-Debug-60af940d15d8bc09364c.json",
					"name" : "CH05_5-11",
					"projectIndex" : 0
				},
				{
					"directoryIndex" : 0,
					"id" : "CH05_5-12::@6890427a1f51a3e7e1df",
					"jsonFile" : "target-CH05_5-12-Debug-b1f8e20458b294b37d2d.json",
					"name" : "CH05_5-12",
					"projectIndex" : 0
				},
				{
					"directoryIndex" : 0,
					"id" : "C_Study::@6890427a1f51a3e7e1df",
					"jsonFile" : "target-C_Study-Debug-5db4aab5db121a18d437.json",
					"name" : "C_Study",
					"projectIndex" : 0
				},
				{
					"directoryIndex" : 0,
					"id" : "DiffiHellman::@6890427a1f51a3e7e1df",
					"jsonFile" : "target-DiffiHellman-Debug-6f022c7c134b05d48f1b.json",
					"name" : "DiffiHellman",
					"projectIndex" : 0
				},
				{
					"directoryIndex" : 0,
					"id" : "main::@6890427a1f51a3e7e1df",
					"jsonFile" : "target-main-Debug-7d0237b6a7e4b364a1ad.json",
					"name" : "main",
					"projectIndex" : 0
				},
				{
					"directoryIndex" : 0,
					"id" : "mine03::@6890427a1f51a3e7e1df",
					"jsonFile" : "target-mine03-Debug-120b5f54f9888b34042e.json",
					"name" : "mine03",
					"projectIndex" : 0
				},
				{
					"directoryIndex" : 0,
					"id" : "test::@6890427a1f51a3e7e1df",
					"jsonFile" : "target-test-Debug-64b4bbfbc029de84fce9.json",
					"name" : "test",
					"projectIndex" : 0
				}
			]
		}
	],
	"kind" : "codemodel",
	"paths" : 
	{
		"build" : "/Users/chahyeonjin/Documents/C-Study/cmake-build-debug",
		"source" : "/Users/chahyeonjin/Documents/C-Study"
	},
	"version" : 
	{
		"major" : 2,
		"minor" : 7
	}
}
